crawlerd_web/__init__.py
crawlerd_web/database.py
crawlerd_web/main.py
crawlerd_web/api/__init__.py
crawlerd_web/api/jobs.py
crawlerd_web/api/nodes.py
crawlerd_web/api/projects.py
crawlerd_web/api/status.py
crawlerd_web/static/index.html
crawlerd_web/static/assets/index-54DrP_uy.css
crawlerd_web/static/assets/index-CS-mF-nT.js
crawlerd_web-0.1.1.dist-info/METADATA
crawlerd_web-0.1.1.dist-info/WHEEL
crawlerd_web-0.1.1.dist-info/entry_points.txt
crawlerd_web-0.1.1.dist-info/top_level.txt
crawlerd_web-0.1.1.dist-info/RECORD
