Metadata-Version: 2.4
Name: crawlerd_web
Version: 0.1.1
Summary: Crawlerd Web Dashboard
Author-email: HuangJiaJia <you@example.com>
License: MIT
Requires-Python: >=3.11
Requires-Dist: python-json-logger==4.0.0
Requires-Dist: fastapi==0.122.0
Requires-Dist: uvicorn==0.38.0
Requires-Dist: apscheduler==3.11.1
Requires-Dist: python-multipart==0.0.20
Requires-Dist: httpx
